metaheuristic_designer/Algorithm.py
metaheuristic_designer/Encoding.py
metaheuristic_designer/Initializer.py
metaheuristic_designer/ObjectiveFunc.py
metaheuristic_designer/Operator.py
metaheuristic_designer/ParamScheduler.py
metaheuristic_designer/Population.py
metaheuristic_designer/SearchStrategy.py
metaheuristic_designer/SelectionMethod.py
metaheuristic_designer/__init__.py
metaheuristic_designer/utils.py
metaheuristic_designer/algorithms/AlgorithmSelection.py
metaheuristic_designer/algorithms/GeneralAlgorithm.py
metaheuristic_designer/algorithms/MemeticAlgorithm.py
metaheuristic_designer/algorithms/StrategySelection.py
metaheuristic_designer/algorithms/__init__.py
metaheuristic_designer/benchmarks/__init__.py
metaheuristic_designer/benchmarks/benchmark_funcs.py
metaheuristic_designer/benchmarks/classic_problems.py
metaheuristic_designer/benchmarks/img_funcs.py
metaheuristic_designer/encodings/AdaptionEncoding.py
metaheuristic_designer/encodings/CMAEncoding.py
metaheuristic_designer/encodings/CompositeEncoding.py
metaheuristic_designer/encodings/DefaultEncoding.py
metaheuristic_designer/encodings/EncodingFromLambda.py
metaheuristic_designer/encodings/ImageEncoding.py
metaheuristic_designer/encodings/MatrixEncoding.py
metaheuristic_designer/encodings/TypeCastEncoding.py
metaheuristic_designer/encodings/__init__.py
metaheuristic_designer/initializers/DirectInitializer.py
metaheuristic_designer/initializers/GaussianInitializer.py
metaheuristic_designer/initializers/InitializerFromLambda.py
metaheuristic_designer/initializers/PermInitializer.py
metaheuristic_designer/initializers/SeedInitializer.py
metaheuristic_designer/initializers/UniformInitializer.py
metaheuristic_designer/initializers/__init__.py
metaheuristic_designer/operators/OperatorAdaptative.py
metaheuristic_designer/operators/OperatorFromLambda.py
metaheuristic_designer/operators/OperatorMeta.py
metaheuristic_designer/operators/OperatorNull.py
metaheuristic_designer/operators/OperatorPerm.py
metaheuristic_designer-0.2.2.dist-info/LICENSE
metaheuristic_designer-0.2.2.dist-info/METADATA
metaheuristic_designer-0.2.2.dist-info/WHEEL
metaheuristic_designer-0.2.2.dist-info/top_level.txt
metaheuristic_designer-0.2.2.dist-info/RECORD
