Metadata-Version: 2.2
Name: metaheuristic-designer
Version: 0.2.2
Summary: A python package to desing metaheuristic optimization algorithms from components.
Author-email: eugenioLR <eugeniolorente0@gmail.com>
License: LICENSE
Project-URL: Homepage, https://github.com/eugenioLR/metaheuristic-designer
Keywords: optization,genetic-algorithm,evolutionary-algorithms,metaheuristics
Requires-Python: >=3.10
License-File: LICENSE
Requires-Dist: matplotlib>=3.5
Requires-Dist: numpy>=1.21
Requires-Dist: scipy>=1.8
Requires-Dist: pyparsing>=3.0
Requires-Dist: scikit-image>=0.21
Requires-Dist: pandas>=2.1.2
Requires-Dist: enlighten>=1.12.2
Provides-Extra: dev
Requires-Dist: nox>=2023.4.22; extra == "dev"
Requires-Dist: pytest>=7.4.0; extra == "dev"
Requires-Dist: coverage>=7.3.1; extra == "dev"
Requires-Dist: sphinx_material>=0.0.36; extra == "dev"
Requires-Dist: sphinx>=7.1.1; extra == "dev"
Requires-Dist: black[jupyter]>=23.10.1; extra == "dev"
Requires-Dist: pygame>=2.5.0; extra == "dev"
Requires-Dist: networkx>=3.1; extra == "dev"
Requires-Dist: opencv-python>=4.8; extra == "dev"
Provides-Extra: examples
Requires-Dist: pygame>=2.5.0; extra == "examples"
Requires-Dist: networkx>=3.1; extra == "examples"
Requires-Dist: opencv-python>=4.8; extra == "examples"
